misas/__init__.py
misas/_modidx.py
misas/_nbdev.py
misas/batch.py
misas/core.py
misas/fastai_model.py
misas/mri.py
misas/tensorflow_model.py
misas-0.1.1.dist-info/LICENSE
misas-0.1.1.dist-info/METADATA
misas-0.1.1.dist-info/WHEEL
misas-0.1.1.dist-info/entry_points.txt
misas-0.1.1.dist-info/top_level.txt
misas-0.1.1.dist-info/RECORD
