Metadata-Version: 2.1
Name: misas
Version: 0.1.1
Summary: Model Interpretation through Sensitivity Analysis for Segmentation
Home-page: https://github.com/chfc-cmi/misas/
Author: Markus J. Ankenbrand
Author-email: markus.ankenbrand@uni-wuerzburg.de
License: MIT License
Keywords: interpretability,explainability,machine learning,sensitivity,augmentation
Classifier: Development Status :: 3 - Alpha
Classifier: Intended Audience :: Developers
Classifier: Natural Language :: English
Classifier: Programming Language :: Python :: 3.7
Classifier: Programming Language :: Python :: 3.8
Classifier: Programming Language :: Python :: 3.9
Classifier: Programming Language :: Python :: 3.10
Classifier: License :: OSI Approved :: MIT License
Requires-Python: >=3.7
License-File: LICENSE
Requires-Dist: matplotlib
Requires-Dist: pillow
Requires-Dist: altair
Requires-Dist: pydicom
Requires-Dist: torchio
Provides-Extra: dev
Requires-Dist: fastai ; extra == 'dev'
Requires-Dist: tensorflow ; extra == 'dev'
Requires-Dist: kornia ; extra == 'dev'
Requires-Dist: scikit-image ; extra == 'dev'
Requires-Dist: ipywidgets ; extra == 'dev'
